{
  "id": 48,
  "category": "tips-lower-back-stretch-relief",
  "theme": "Lower Back Stretch Relief Tips Tips and Best Practices",
  "title": "Proven Strategies for Lower Back Stretch Relief Tips Tips and Best Practices",
  "slug": "proven-strategies-for-lower-back-stretch-relief-tips-tips-and-best-practices",
  "meta_description": "Learn about Lower Back Stretch Relief Tips Tips and Best Practices from the ground up. Our comprehensive guide covers everything you need to start your journey with confidence.",
  "content": "Let's dive into the exciting world of Lower Back Stretch Relief Tips Tips and Best Practices. This guide is designed to be both informative and practical, giving you the tools and knowledge you need to succeed. From basic principles to real-world applications, we cover it all.\n\n<h2>Recommended Resources</h2>\n<p>Equip yourself for success. Here, we'll highlight the best tools, resources, and materials available to help you learn effectively and achieve excellent results.</p>\n<p>It's also important to note that Equip yourself for success. here, we'll highlight the best tools, resources, and materials available to help you learn effectively and achieve excellent results.</p>\n\n<h2>Common Challenges</h2>\n<p>Additionally, Being prepared means knowing what to expect. here, we'll discuss the common challenges and pitfalls people face, along with practical strategies to overcome them and keep moving forward.</p>\n<p>Being prepared means knowing what to expect. Here, we'll discuss the common challenges and pitfalls people face, along with practical strategies to overcome them and keep moving forward.</p>\n\n<h2>Historical Context</h2>\n<p>Looking at the historical development reveals why certain aspects are emphasized today. This perspective adds richness to your understanding and appreciation. The practical application of these ideas yields remarkable results when done correctly.</p>\n\n<h2>Walkthrough</h2>\n<p>A systematic approach ensures you don't miss anything important. Here, we present the process in a logical sequence that builds momentum as you progress.</p>\n\n<h2>Ask the Experts</h2>\n<p>We've gathered the most frequently asked questions about this topic and provided thorough, expert answers. This covers the questions people most often have when starting out.</p>\n<p>When you think about it, We've gathered the most frequently asked questions about this topic and provided thorough, expert answers. this covers the questions people most often have when starting out.</p>\n<p>The practical application of these ideas yields remarkable results when done correctly.</p>\n\n<h2>Real-World Examples</h2>\n<p>Moreover, Nothing beats seeing concepts in action. this section explores real-world examples and case studies that demonstrate how these principles work in practical situations. learn from actual success stories.</p>\n<p>Nothing beats seeing concepts in action. This section explores real-world examples and case studies that demonstrate how these principles work in practical situations. Learn from actual success stories.</p>\n\n<h2>Options Explored</h2>\n<p>Additionally, There are multiple ways to approach this topic, each with its own strengths. this section compares different methodologies to help you choose what works best for you.</p>\n<p>There are multiple ways to approach this topic, each with its own strengths. This section compares different methodologies to help you choose what works best for you.</p>\n\n<h2>Historical Context</h2>\n<p>From humble beginnings to widespread adoption, the story of how this subject developed is fascinating and informative. We trace its journey through time.</p>\n<p>In addition, From humble beginnings to widespread adoption, the story of how this subject developed is fascinating and informative. we trace its journey through time.</p>\n\n<h2>Best Practices</h2>\n<p>What do the experts recommend? Let's look at proven strategies and best practices that have stood the test of time. Implementing these will help you achieve better results more efficiently. This approach has been validated through extensive research and real-world testing.</p>\n\n<h2>The Advantages</h2>\n<p>What makes this worth learning? Let's explore the many benefits and advantages that come from understanding and applying these principles. From professional growth to personal satisfaction, the rewards are significant.</p>\n<p>To elaborate further, What makes this worth learning? let's explore the many benefits and advantages that come from understanding and applying these principles. from professional growth to personal satisfaction, the rewards are significant.</p>\n<p>Many experts agree that this is one of the most reliable methods available.</p>\n\nAs we wrap up this guide on Lower Back Stretch Relief Tips Tips and Best Practices, it's clear that this is a subject with depth and potential. We've covered the essentials, explored key concepts, and provided practical advice that you can start using immediately. Keep learning, keep practicing, and you'll continue to see progress and improvement over time. Thank you for joining us on this journey!",
  "created_at": "2026-06-05T13:48:30.463795",
  "word_count": 644,
  "seo": {
    "keywords": [
      "lower back stretch relief tips tips and best practices",
      "tips-lower-back-stretch-relief",
      "Lower Back Stretch Relief Tips Tips and Best Practices guide",
      "best Lower Back Stretch Relief Tips Tips and Best Practices",
      "Lower Back Stretch Relief Tips Tips and Best Practices tips",
      "Lower Back Stretch Relief Tips Tips and Best Practices 2026",
      "how to lower back stretch relief tips tips and best practices"
    ],
    "title_tag": "Proven Strategies for Lower Back Stretch Relief Tips Tips and Best Practices | lower-back-stretch-relief",
    "meta_description": "Learn about Lower Back Stretch Relief Tips Tips and Best Practices from the ground up. Our comprehensive guide covers everything you need to start your journey with confidence.",
    "og_title": "Proven Strategies for Lower Back Stretch Relief Tips Tips and Best Practices",
    "og_description": "Learn about Lower Back Stretch Relief Tips Tips and Best Practices from the ground up. Our comprehensive guide covers everything you need to start your journey with confidence.",
    "og_type": "article",
    "twitter_card": "summary_large_image",
    "canonical_url": "/proven-strategies-for-lower-back-stretch-relief-tips-tips-and-best-practices",
    "robots": "index, follow"
  },
  "geo": {
    "country": "Germany",
    "city": "Hamburg",
    "language": "en",
    "target_regions": [
      "North America",
      "Europe",
      "Asia Pacific"
    ]
  },
  "image": {
    "id": "3c8ac1f7af884ca89fbfa66c85b723addfc6b251701a1e13b1d47a2a8d0ea3e5",
    "url": "https://picsum.photos/1145/414?random=250",
    "alt": "Featured image for: Proven Strategies for Lower Back Stretch Relief Tips Tips and Best Practices",
    "width": 1145,
    "height": 414
  }
}