{
  "id": 64,
  "category": "history-lower-back-stretch-relief",
  "theme": "Common Mistakes in Lower Back Stretch Relief History",
  "title": "Common Mistakes in Lower Back Stretch Relief History: From Beginner to Expert",
  "slug": "common-mistakes-in-lower-back-stretch-relief-history-from-beginner-to-expert",
  "meta_description": "Everything you've ever wanted to know about Common Mistakes in Lower Back Stretch Relief History in one place. Practical, actionable, and easy to understand.",
  "content": "Understanding Common Mistakes in Lower Back Stretch Relief History can open up new possibilities and opportunities. In this article, we'll break down this complex topic into easy-to-follow sections, making it accessible to everyone. Get ready to expand your knowledge and skills!\n\n**Key Statistic**: $4,500 average annual savings from implementing these strategies (Economic Impact Analysis)\n\n<h2>Advanced Techniques</h2>\n<p>Additionally, Once you've mastered the fundamentals, what's next? let's explore advanced techniques and strategies that will help you elevate your skills and knowledge to new heights.</p>\n<p>Once you've mastered the fundamentals, what's next? Let's explore advanced techniques and strategies that will help you elevate your skills and knowledge to new heights.</p>\n\n<h2>Myth Busting</h2>\n<p>Misinformation can hold you back. In this section, we'll debunk common myths and misconceptions about this subject, helping you build your knowledge on a solid foundation of truth.</p>\n<p>To elaborate further, Misinformation can hold you back. in this section, we'll debunk common myths and misconceptions about this subject, helping you build your knowledge on a solid foundation of truth.</p>\n\n<h2>Recommended Resources</h2>\n<p>What tools and resources should you be using? Let's explore the essential materials, tools, and resources that will support your learning and help you achieve your goals.</p>\n<p>Furthermore, What tools and resources should you be using? let's explore the essential materials, tools, and resources that will support your learning and help you achieve your goals.</p>\n<p>The practical application of these ideas yields remarkable results when done correctly.</p>\n\n<h2>Expert Q&A</h2>\n<p>To elaborate further, Learn from others' curiosity. here are answers to the questions that come up again and again in forums, discussions, and workshops about this subject.</p>\n<p>Learn from others' curiosity. Here are answers to the questions that come up again and again in forums, discussions, and workshops about this subject.</p>\n\n📌 **Quick Fact**: Surprising: Many experts actually started with a very different approach before finding success.\n\n<h2>Looking Ahead</h2>\n<p>The only constant is change. Let's explore what the future might hold for this subject, including emerging trends, new technologies, and evolving best practices you should be aware of. The practical application of these ideas yields remarkable results when done correctly.</p>\n\n<h2>Expert Tips</h2>\n<p>Explore proven strategies and techniques that experts recommend. These best practices have been tested and refined through real-world application, ensuring you get the best results possible from your efforts.</p>\n<p>In this context, Explore proven strategies and techniques that experts recommend. these best practices have been tested and refined through real-world application, ensuring you get the best results possible from your efforts.</p>\n\n<h2>Potential Pitfalls</h2>\n<p>No learning process is without challenges. Let's identify common obstacles you might encounter and, more importantly, learn how to overcome them effectively.</p>\n\n<h2>Options Explored</h2>\n<p>Not every approach works for everyone. Here, we look at various strategies and discuss when to use which method for optimal results. This approach has been validated through extensive research and real-world testing.</p>\n\n<h2>Common Misconceptions</h2>\n<p>There are many myths and misunderstandings surrounding this topic. Let's set the record straight by addressing common misconceptions and separating fact from fiction.</p>\n<p>Moreover, There are many myths and misunderstandings surrounding this topic. let's set the record straight by addressing common misconceptions and separating fact from fiction.</p>\n\n<h2>Comparative Analysis</h2>\n<p>Understanding the options helps you make informed decisions. We examine different schools of thought and their practical applications in real-world scenarios.</p>\n<p>Moreover, Understanding the options helps you make informed decisions. we examine different schools of thought and their practical applications in real-world scenarios.</p>\n<p>These principles form the backbone of effective practice in this field.</p>\n\n<h2>Future Outlook</h2>\n<p>The only constant is change. Let's explore what the future might hold for this subject, including emerging trends, new technologies, and evolving best practices you should be aware of. These principles form the backbone of effective practice in this field.</p>\n\n<h2>Different Approaches</h2>\n<p>Not every approach works for everyone. Here, we look at various strategies and discuss when to use which method for optimal results.</p>\n<p>When you think about it, Not every approach works for everyone. here, we look at various strategies and discuss when to use which method for optimal results.</p>\n<p>These principles form the backbone of effective practice in this field.</p>\n\nCommon Mistakes in Lower Back Stretch Relief History is a journey, not a destination. We hope this guide has provided you with the knowledge and confidence to take your first steps or to continue advancing on your path. Keep practicing, stay curious, and never stop learning. The best is yet to come!",
  "created_at": "2026-06-05T13:48:30.467283",
  "word_count": 732,
  "seo": {
    "keywords": [
      "common mistakes in lower back stretch relief history",
      "history-lower-back-stretch-relief",
      "Common Mistakes in Lower Back Stretch Relief History guide",
      "best Common Mistakes in Lower Back Stretch Relief History",
      "Common Mistakes in Lower Back Stretch Relief History tips",
      "Common Mistakes in Lower Back Stretch Relief History 2026",
      "how to common mistakes in lower back stretch relief history"
    ],
    "title_tag": "Common Mistakes in Lower Back Stretch Relief History: From Beginner to Expert | lower-back-stretch-relief",
    "meta_description": "Everything you've ever wanted to know about Common Mistakes in Lower Back Stretch Relief History in one place. Practical, actionable, and easy to understand.",
    "og_title": "Common Mistakes in Lower Back Stretch Relief History: From Beginner to Expert",
    "og_description": "Everything you've ever wanted to know about Common Mistakes in Lower Back Stretch Relief History in one place. Practical, actionable, and easy to understand.",
    "og_type": "article",
    "twitter_card": "summary_large_image",
    "canonical_url": "/common-mistakes-in-lower-back-stretch-relief-history-from-beginner-to-expert",
    "robots": "index, follow"
  },
  "geo": {
    "country": "France",
    "city": "Nice",
    "language": "en",
    "target_regions": [
      "North America",
      "Europe",
      "Asia Pacific"
    ]
  },
  "image": {
    "id": "e855859bfffcfbae4fde309a31cbdf016f045b9fe8ee03adbd0bcd8fca2169d8",
    "url": "https://picsum.photos/819/460?random=88",
    "alt": "Featured image for: Common Mistakes in Lower Back Stretch Relief History: From Beginner to Expert",
    "width": 819,
    "height": 460
  }
}